LnkAnalyser/__init__.py
LnkAnalyser/lnkanalyser.py
LnkAnalyser/read.py
LnkAnalyser-0.0.6.dist-info/LICENSE
LnkAnalyser-0.0.6.dist-info/METADATA
LnkAnalyser-0.0.6.dist-info/WHEEL
LnkAnalyser-0.0.6.dist-info/top_level.txt
LnkAnalyser-0.0.6.dist-info/RECORD
