Metadata-Version: 2.1
Name: LnkAnalyser
Version: 0.0.6
Summary: A Python package for analysing Windows shortcut files
Home-page: https://ajweir.co.uk/projects/lnk-analyser
Author: Andrew Weir
Author-email: andrew@ajweir.co.uk
License: UNKNOWN
Platform: UNKNOWN
Classifier: Programming Language :: Python :: 3
Classifier: License :: OSI Approved :: MIT License
Classifier: Operating System :: OS Independent
Requires-Python: >=3.9
